ZhongguoQiye2020RengongzhinengYingyongShijianYuQushiFix1/README.md
ZhongguoQiye2020RengongzhinengYingyongShijianYuQushiFix1/__init__.py
ZhongguoQiye2020RengongzhinengYingyongShijianYuQushiFix1/__main__.py
ZhongguoQiye2020RengongzhinengYingyongShijianYuQushiFix1/file.pdf
ZhongguoQiye2020RengongzhinengYingyongShijianYuQushiFix1/index.html
zhongguo_qiye_2020_rengongzhineng_yingyong_shijian_yu_qushi_fix1-2025.3.25.0.dist-info/METADATA
zhongguo_qiye_2020_rengongzhineng_yingyong_shijian_yu_qushi_fix1-2025.3.25.0.dist-info/WHEEL
zhongguo_qiye_2020_rengongzhineng_yingyong_shijian_yu_qushi_fix1-2025.3.25.0.dist-info/entry_points.txt
zhongguo_qiye_2020_rengongzhineng_yingyong_shijian_yu_qushi_fix1-2025.3.25.0.dist-info/top_level.txt
zhongguo_qiye_2020_rengongzhineng_yingyong_shijian_yu_qushi_fix1-2025.3.25.0.dist-info/RECORD
